steadynlp/__init__.py
steadynlp/preprocessing/__init__.py
steadynlp/preprocessing/hashtag_processing_utils.py
steadynlp/preprocessing/text_processing_utils.py
steadynlp/textranking/TextRanking.py
steadynlp/textranking/__init__.py
steadynlp/textranking/_sentenceranking.py
steadynlp/textranking/_wordranking.py
steadynlp-0.0.2.dist-info/LICENSE
steadynlp-0.0.2.dist-info/METADATA
steadynlp-0.0.2.dist-info/WHEEL
steadynlp-0.0.2.dist-info/dependency_links.txt
steadynlp-0.0.2.dist-info/top_level.txt
steadynlp-0.0.2.dist-info/RECORD
